Workbook

Sheet Panduan & Soal Latihan
A1: STUDY CASE: NUSANTARA MART RETAIL SALES ANALYSIS (1.000 TRANSAKSI)
A2: Studi kasus ini dirancang khusus untuk menguji dan melatih keterampilan analisis data Excel dari tingkat dasar hingga mahir.
A4: A. STRUKTUR SHEET DI WORKBOOK INI
A5: 1. Raw_Data_Transaksi : Berisi 1.000 baris data transaksi asli sepanjang tahun 2025.
A6: 2. Master_Produk : Tabel referensi harga, modal (COGS), dan kategori 15 produk.
A7: 3. Master_Sales : Tabel referensi data tim sales, wilayah (Region), dan kantor cabang (Branch).
A8: 4. Lembar_Kerja_Analisis : Sheet kerja utama tempat Anda mengerjakan penggabungan data dan formula.
A10: B. DAFTAR TUGAS DAN SOAL LATIHAN TERARAH
A12: MODUL 1: LOOKUP & INDEX MATCH (MENGISI SHEET 'Lembar_Kerja_Analisis')
A13: Soal 1.1: Isi kolom C (Sales_Name) menggunakan rumus VLOOKUP atau XLOOKUP dengan mencocokkan Sales_ID dari Raw_Data_Transaksi ke tabel Master_Sales.
A14: Soal 1.2: Isi kolom D (Region) dan kolom E (Branch) menggunakan INDEX & MATCH berdasarkan Sales_ID.
A15: Soal 1.3: Isi kolom F (Product_Name) dan G (Category) dengan referensi ke tabel Master_Produk menggunakan Product_ID dari Raw_Data_Transaksi.
... A49: Soal 4.4: Hubungkan Slicer Interaktif (Slicer Region dan Slicer Category) ke grafik yang Anda buat sehingga grafik dapat difilter secara dinamis.

Sheet Raw_Data_Transaksi
A1: Transaction_ID | B1: Order_Date | C1: Sales_ID | D1: Product_ID | E1: Qty | F1: Discount_Pct | G1: Sales_Channel | H1: Customer_Type | I1: Payment_Method
A2: TRX-2025-0001 | B2: 45985 | C2: SLS-01 | D2: PRD-102 | E2: 12 | F2: 0.1 | G2: Website Toko | H2: Retail | I2: Kartu Kredit
A3: TRX-2025-0002 | B3: 45710 | C3: SLS-02 | D3: PRD-111 | E3: 16 | F3: 0 | G3: Online Marketplace | H3: Retail | I3: Kartu Kredit
A4: TRX-2025-0003 | B4: 45777 | C4: SLS-01 | D4: PRD-109 | E4: 9 | F4: 0.2 | G4: B2B Corporate | H4: Retail | I4: COD
A5: TRX-2025-0004 | B5: 45959 | C5: SLS-01 | D5: PRD-105 | E5: 3 | F5: 0.15 | G5: Direct Store | H5: Corporate | I5: Kartu Kredit
A6: TRX-2025-0005 | B6: 45768 | C6: SLS-06 | D6: PRD-113 | E6: 2 | F6: 0 | G6: B2B Corporate | H6: Retail | I6: E-Wallet
A7: TRX-2025-0006 | B7: 45834 | C7: SLS-05 | D7: PRD-110 | E7: 26 | F7: 0.15 | G7: Online Marketplace | H7: Corporate | I7: Transfer Bank
A8: TRX-2025-0007 | B8: 45940 | C8: SLS-06 | D8: PRD-105 | E8: 10 | F8: 0.05 | G8: Online Marketplace | H8: Retail | I8: Kartu Kredit
A9: TRX-2025-0008 | B9: 45806 | C9: SLS-04 | D9: PRD-102 | E9: 2 | F9: 0.15 | G9: Direct Store | H9: Corporate | I9: E-Wallet
A10: TRX-2025-0009 | B10: 45741 | C10: SLS-06 | D10: PRD-106 | E10: 4 | F10: 0.1 | G10: Online Marketplace | H10: Member VIP | I10: Kartu Kredit
A11: TRX-2025-0010 | B11: 45931 | C11: SLS-04 | D11: PRD-112 | E11: 17 | F11: 0.15 | G11: Direct Store | H11: Member VIP | I11: Kartu Kredit
A12: TRX-2025-0011 | B12: 46008 | C12: SLS-01 | D12: PRD-106 | E12: 4 | F12: 0 | G12: Direct Store | H12: Corporate | I12: E-Wallet
A13: TRX-2025-0012 | B13: 45691 | C13: SLS-06 | D13: PRD-104 | E13: 4 | F13: 0.15 | G13: B2B Corporate | H13: Member VIP | I13: COD
... A1001: TRX-2025-1000 | B1001: 45916 | C1001: SLS-07 | D1001: PRD-110 | E1001: 15 | F1001: 0.1 | G1001: Website Toko | H1001: Member VIP | I1001: Transfer Bank

Sheet Master_Produk
A1: Product_ID | B1: Product_Name | C1: Category | D1: Unit_Price | E1: Cost_Price
A2: PRD-101 | B2: Laptop Ultrabook 14" | C2: Elektronik | D2: 8500000 | E2: 7200000
A3: PRD-102 | B3: Wireless Mouse Ergonomic | C3: Elektronik | D3: 250000 | E3: 160000
A4: PRD-103 | B4: Mechanical Keyboard RGB | C4: Elektronik | D4: 750000 | E4: 520000
A5: PRD-104 | B5: Monitor 24" FHD 144Hz | C5: Elektronik | D5: 1950000 | E5: 1500000
A6: PRD-105 | B6: Kemeja Batik Katun Premium | C6: Fashion | D6: 320000 | E6: 190000
A7: PRD-106 | B7: Celana Chino Slim Fit | C7: Fashion | D7: 280000 | E7: 175000
A8: PRD-107 | B8: Jaket Hoodie Casual | C8: Fashion | D8: 350000 | E8: 220000
A9: PRD-108 | B9: Sepatu Sneakers Pria/Wanita | C9: Fashion | D9: 450000 | E9: 290000
A10: PRD-109 | B10: Kopi Arabika Gayo 250g | C10: F&B | D10: 85000 | E10: 55000
A11: PRD-110 | B11: Minyak Goreng Sawit 2L | C11: F&B | D11: 36000 | E11: 31000
A12: PRD-111 | B12: Beras Premium 5kg | C12: F&B | D12: 74000 | E12: 65000
A13: PRD-112 | B13: Susu UHT Full Cream 1L | C13: F&B | D13: 22000 | E13: 18000
... A16: PRD-115 | B16: Set Pisau Dapur Stainless | C16: Peralatan Rumah | D16: 165000 | E16: 105000

Sheet Master_Sales
A1: Sales_ID | B1: Sales_Name | C1: Branch | D1: Region
A2: SLS-01 | B2: Andi Pratama | C2: Jakarta | D2: Barat
A3: SLS-02 | B3: Budi Santoso | C3: Surabaya | D3: Timur
A4: SLS-03 | B4: Citra Lestari | C4: Bandung | D4: Barat
A5: SLS-04 | B5: Dewi Anggraini | C5: Medan | D5: Barat
A6: SLS-05 | B6: Eko Prasetyo | C6: Semarang | D6: Tengah
A7: SLS-06 | B7: Fajar Nugraha | C7: Makassar | D7: Timur
A8: SLS-07 | B8: Gita Permata | C8: Denpasar | D8: Tengah
A9: SLS-08 | B9: Hendra Wijaya | C9: Yogyakarta | D9: Tengah

Sheet Lembar_Kerja_Analisis
C1: Transaction_ID | D1: Order_Date | E1: Sales_Name | F1: Region | G1: Branch | H1: Product_Name | I1: Category | J1: Unit_Price | K1: Cost_Price | L1: Qty | M1: Gross_Revenue | N1: Discount_Pct | O1: Discount_Amount | P1: Net_Revenue | Q1: Total_COGS | R1: Total_Profit
A2: =_xlfn.XLOOKUP(C2,Raw_Data_Transaksi!$A$1:$A$1001,Raw_Data_Transaksi!$D$1:$D$1001,,0) -> PRD-102 | B2: =_xlfn.XLOOKUP(C2,Raw_Data_Transaksi!$A$1:$A$1001,Raw_Data_Transaksi!$C$1:$C$1001,,0) -> SLS-01 | C2: TRX-2025-0001 | D2: 45985 | E2: =VLOOKUP(B2,Master_Sales!$A$1:$D$9,2,FALSE) -> Andi Pratama | F2: =INDEX(Master_Sales!$D$1:$D$9,MATCH(Lembar_Kerja_Analisis!B2,Master_Sales!$A$1:$A$9,0)) -> Barat | G2: =INDEX(Master_Sales!$C$1:$C$9,MATCH(Lembar_Kerja_Analisis!B2,Master_Sales!$A$1:$A$9,0)) -> Jakarta | H2: =VLOOKUP(A2,Master_Produk!$A$1:$E$16,2,FALSE) -> Wireless Mouse Ergonomic | I2: =INDEX(Master_Produk!$C$1:$C$16,MATCH(Lembar_Kerja_Analisis!A2,Master_Produk!$A$1:$A$16,0)) -> Elektronik | J2: =_xlfn.XLOOKUP(A2,Master_Produk!$A$1:$A$16,Master_Produk!$D$1:$D$16,,0) -> 250000 | K2: =INDEX(Master_Produk!$E$1:$E$16,MATCH(Lembar_Kerja_Analisis!A2,Master_Produk!$A$1:$A$16,0)) -> 160000 | L2: 12 | M2: =L2*J2 -> 3000000 | N2: 0.1 | O2: =M2*N2 -> 300000 | P2: =M2-O2 -> 2700000 | Q2: =L2*K2 -> 1920000 | R2: =P2-Q2 -> 780000
A3: =_xlfn.XLOOKUP(C3,Raw_Data_Transaksi!$A$1:$A$1001,Raw_Data_Transaksi!$D$1:$D$1001,,0) -> PRD-111 | B3: =_xlfn.XLOOKUP(C3,Raw_Data_Transaksi!$A$1:$A$1001,Raw_Data_Transaksi!$C$1:$C$1001,,0) -> SLS-02 | C3: TRX-2025-0002 | D3: 45710 | E3: =VLOOKUP(B3,Master_Sales!$A$1:$D$9,2,FALSE) -> Budi Santoso | F3: =INDEX(Master_Sales!$D$1:$D$9,MATCH(Lembar_Kerja_Analisis!B3,Master_Sales!$A$1:$A$9,0)) -> Timur | G3: =INDEX(Master_Sales!$C$1:$C$9,MATCH(Lembar_Kerja_Analisis!B3,Master_Sales!$A$1:$A$9,0)) -> Surabaya | H3: =VLOOKUP(A3,Master_Produk!$A$1:$E$16,2,FALSE) -> Beras Premium 5kg | I3: =INDEX(Master_Produk!$C$1:$C$16,MATCH(Lembar_Kerja_Analisis!A3,Master_Produk!$A$1:$A$16,0)) -> F&B | J3: =_xlfn.XLOOKUP(A3,Master_Produk!$A$1:$A$16,Master_Produk!$D$1:$D$16,,0) -> 74000 | K3: =INDEX(Master_Produk!$E$1:$E$16,MATCH(Lembar_Kerja_Analisis!A3,Master_Produk!$A$1:$A$16,0)) -> 65000 | L3: 16 | M3: =L3*J3 -> 1184000 | N3: 0 | O3: =M3*N3 -> 0 | P3: =M3-O3 -> 1184000 | Q3: =L3*K3 -> 1040000 | R3: =P3-Q3 -> 144000
A4: =_xlfn.XLOOKUP(C4,Raw_Data_Transaksi!$A$1:$A$1001,Raw_Data_Transaksi!$D$1:$D$1001,,0) -> PRD-109 | B4: =_xlfn.XLOOKUP(C4,Raw_Data_Transaksi!$A$1:$A$1001,Raw_Data_Transaksi!$C$1:$C$1001,,0) -> SLS-01 | C4: TRX-2025-0003 | D4: 45777 | E4: =VLOOKUP(B4,Master_Sales!$A$1:$D$9,2,FALSE) -> Andi Pratama | F4: =INDEX(Master_Sales!$D$1:$D$9,MATCH(Lembar_Kerja_Analisis!B4,Master_Sales!$A$1:$A$9,0)) -> Barat | G4: =INDEX(Master_Sales!$C$1:$C$9,MATCH(Lembar_Kerja_Analisis!B4,Master_Sales!$A$1:$A$9,0)) -> Jakarta | H4: =VLOOKUP(A4,Master_Produk!$A$1:$E$16,2,FALSE) -> Kopi Arabika Gayo 250g | I4: =INDEX(Master_Produk!$C$1:$C$16,MATCH(Lembar_Kerja_Analisis!A4,Master_Produk!$A$1:$A$16,0)) -> F&B | J4: =_xlfn.XLOOKUP(A4,Master_Produk!$A$1:$A$16,Master_Produk!$D$1:$D$16,,0) -> 85000 | K4: =INDEX(Master_Produk!$E$1:$E$16,MATCH(Lembar_Kerja_Analisis!A4,Master_Produk!$A$1:$A$16,0)) -> 55000 | L4: 9 | M4: =L4*J4 -> 765000 | N4: 0.2 | O4: =M4*N4 -> 153000 | P4: =M4-O4 -> 612000 | Q4: =L4*K4 -> 495000 | R4: =P4-Q4 -> 117000
A5: =_xlfn.XLOOKUP(C5,Raw_Data_Transaksi!$A$1:$A$1001,Raw_Data_Transaksi!$D$1:$D$1001,,0) -> PRD-105 | B5: =_xlfn.XLOOKUP(C5,Raw_Data_Transaksi!$A$1:$A$1001,Raw_Data_Transaksi!$C$1:$C$1001,,0) -> SLS-01 | C5: TRX-2025-0004 | D5: 45959 | E5: =VLOOKUP(B5,Master_Sales!$A$1:$D$9,2,FALSE) -> Andi Pratama | F5: =INDEX(Master_Sales!$D$1:$D$9,MATCH(Lembar_Kerja_Analisis!B5,Master_Sales!$A$1:$A$9,0)) -> Barat | G5: =INDEX(Master_Sales!$C$1:$C$9,MATCH(Lembar_Kerja_Analisis!B5,Master_Sales!$A$1:$A$9,0)) -> Jakarta | H5: =VLOOKUP(A5,Master_Produk!$A$1:$E$16,2,FALSE) -> Kemeja Batik Katun Premium | I5: =INDEX(Master_Produk!$C$1:$C$16,MATCH(Lembar_Kerja_Analisis!A5,Master_Produk!$A$1:$A$16,0)) -> Fashion | J5: =_xlfn.XLOOKUP(A5,Master_Produk!$A$1:$A$16,Master_Produk!$D$1:$D$16,,0) -> 320000 | K5: =INDEX(Master_Produk!$E$1:$E$16,MATCH(Lembar_Kerja_Analisis!A5,Master_Produk!$A$1:$A$16,0)) -> 190000 | L5: 3 | M5: =L5*J5 -> 960000 | N5: 0.15 | O5: =M5*N5 -> 144000 | P5: =M5-O5 -> 816000 | Q5: =L5*K5 -> 570000 | R5: =P5-Q5 -> 246000
A6: =_xlfn.XLOOKUP(C6,Raw_Data_Transaksi!$A$1:$A$1001,Raw_Data_Transaksi!$D$1:$D$1001,,0) -> PRD-113 | B6: =_xlfn.XLOOKUP(C6,Raw_Data_Transaksi!$A$1:$A$1001,Raw_Data_Transaksi!$C$1:$C$1001,,0) -> SLS-06 | C6: TRX-2025-0005 | D6: 45768 | E6: =VLOOKUP(B6,Master_Sales!$A$1:$D$9,2,FALSE) -> Fajar Nugraha | F6: =INDEX(Master_Sales!$D$1:$D$9,MATCH(Lembar_Kerja_Analisis!B6,Master_Sales!$A$1:$A$9,0)) -> Timur | G6: =INDEX(Master_Sales!$C$1:$C$9,MATCH(Lembar_Kerja_Analisis!B6,Master_Sales!$A$1:$A$9,0)) -> Makassar | H6: =VLOOKUP(A6,Master_Produk!$A$1:$E$16,2,FALSE) -> Wajan Anti Lengket 28cm | I6: =INDEX(Master_Produk!$C$1:$C$16,MATCH(Lembar_Kerja_Analisis!A6,Master_Produk!$A$1:$A$16,0)) -> Peralatan Rumah | J6: =_xlfn.XLOOKUP(A6,Master_Produk!$A$1:$A$16,Master_Produk!$D$1:$D$16,,0) -> 210000 | K6: =INDEX(Master_Produk!$E$1:$E$16,MATCH(Lembar_Kerja_Analisis!A6,Master_Produk!$A$1:$A$16,0)) -> 140000 | L6: 2 | M6: =L6*J6 -> 420000 | N6: 0 | O6: =M6*N6 -> 0 | P6: =M6-O6 -> 420000 | Q6: =L6*K6 -> 280000 | R6: =P6-Q6 -> 140000
A7: =_xlfn.XLOOKUP(C7,Raw_Data_Transaksi!$A$1:$A$1001,Raw_Data_Transaksi!$D$1:$D$1001,,0) -> PRD-110 | B7: =_xlfn.XLOOKUP(C7,Raw_Data_Transaksi!$A$1:$A$1001,Raw_Data_Transaksi!$C$1:$C$1001,,0) -> SLS-05 | C7: TRX-2025-0006 | D7: 45834 | E7: =VLOOKUP(B7,Master_Sales!$A$1:$D$9,2,FALSE) -> Eko Prasetyo | F7: =INDEX(Master_Sales!$D$1:$D$9,MATCH(Lembar_Kerja_Analisis!B7,Master_Sales!$A$1:$A$9,0)) -> Tengah | G7: =INDEX(Master_Sales!$C$1:$C$9,MATCH(Lembar_Kerja_Analisis!B7,Master_Sales!$A$1:$A$9,0)) -> Semarang | H7: =VLOOKUP(A7,Master_Produk!$A$1:$E$16,2,FALSE) -> Minyak Goreng Sawit 2L | I7: =INDEX(Master_Produk!$C$1:$C$16,MATCH(Lembar_Kerja_Analisis!A7,Master_Produk!$A$1:$A$16,0)) -> F&B | J7: =_xlfn.XLOOKUP(A7,Master_Produk!$A$1:$A$16,Master_Produk!$D$1:$D$16,,0) -> 36000 | K7: =INDEX(Master_Produk!$E$1:$E$16,MATCH(Lembar_Kerja_Analisis!A7,Master_Produk!$A$1:$A$16,0)) -> 31000 | L7: 26 | M7: =L7*J7 -> 936000 | N7: 0.15 | O7: =M7*N7 -> 140400 | P7: =M7-O7 -> 795600 | Q7: =L7*K7 -> 806000 | R7: =P7-Q7 -> -10400
A8: =_xlfn.XLOOKUP(C8,Raw_Data_Transaksi!$A$1:$A$1001,Raw_Data_Transaksi!$D$1:$D$1001,,0) -> PRD-105 | B8: =_xlfn.XLOOKUP(C8,Raw_Data_Transaksi!$A$1:$A$1001,Raw_Data_Transaksi!$C$1:$C$1001,,0) -> SLS-06 | C8: TRX-2025-0007 | D8: 45940 | E8: =VLOOKUP(B8,Master_Sales!$A$1:$D$9,2,FALSE) -> Fajar Nugraha | F8: =INDEX(Master_Sales!$D$1:$D$9,MATCH(Lembar_Kerja_Analisis!B8,Master_Sales!$A$1:$A$9,0)) -> Timur | G8: =INDEX(Master_Sales!$C$1:$C$9,MATCH(Lembar_Kerja_Analisis!B8,Master_Sales!$A$1:$A$9,0)) -> Makassar | H8: =VLOOKUP(A8,Master_Produk!$A$1:$E$16,2,FALSE) -> Kemeja Batik Katun Premium | I8: =INDEX(Master_Produk!$C$1:$C$16,MATCH(Lembar_Kerja_Analisis!A8,Master_Produk!$A$1:$A$16,0)) -> Fashion | J8: =_xlfn.XLOOKUP(A8,Master_Produk!$A$1:$A$16,Master_Produk!$D$1:$D$16,,0) -> 320000 | K8: =INDEX(Master_Produk!$E$1:$E$16,MATCH(Lembar_Kerja_Analisis!A8,Master_Produk!$A$1:$A$16,0)) -> 190000 | L8: 10 | M8: =L8*J8 -> 3200000 | N8: 0.05 | O8: =M8*N8 -> 160000 | P8: =M8-O8 -> 3040000 | Q8: =L8*K8 -> 1900000 | R8: =P8-Q8 -> 1140000
A9: =_xlfn.XLOOKUP(C9,Raw_Data_Transaksi!$A$1:$A$1001,Raw_Data_Transaksi!$D$1:$D$1001,,0) -> PRD-102 | B9: =_xlfn.XLOOKUP(C9,Raw_Data_Transaksi!$A$1:$A$1001,Raw_Data_Transaksi!$C$1:$C$1001,,0) -> SLS-04 | C9: TRX-2025-0008 | D9: 45806 | E9: =VLOOKUP(B9,Master_Sales!$A$1:$D$9,2,FALSE) -> Dewi Anggraini | F9: =INDEX(Master_Sales!$D$1:$D$9,MATCH(Lembar_Kerja_Analisis!B9,Master_Sales!$A$1:$A$9,0)) -> Barat | G9: =INDEX(Master_Sales!$C$1:$C$9,MATCH(Lembar_Kerja_Analisis!B9,Master_Sales!$A$1:$A$9,0)) -> Medan | H9: =VLOOKUP(A9,Master_Produk!$A$1:$E$16,2,FALSE) -> Wireless Mouse Ergonomic | I9: =INDEX(Master_Produk!$C$1:$C$16,MATCH(Lembar_Kerja_Analisis!A9,Master_Produk!$A$1:$A$16,0)) -> Elektronik | J9: =_xlfn.XLOOKUP(A9,Master_Produk!$A$1:$A$16,Master_Produk!$D$1:$D$16,,0) -> 250000 | K9: =INDEX(Master_Produk!$E$1:$E$16,MATCH(Lembar_Kerja_Analisis!A9,Master_Produk!$A$1:$A$16,0)) -> 160000 | L9: 2 | M9: =L9*J9 -> 500000 | N9: 0.15 | O9: =M9*N9 -> 75000 | P9: =M9-O9 -> 425000 | Q9: =L9*K9 -> 320000 | R9: =P9-Q9 -> 105000
A10: =_xlfn.XLOOKUP(C10,Raw_Data_Transaksi!$A$1:$A$1001,Raw_Data_Transaksi!$D$1:$D$1001,,0) -> PRD-106 | B10: =_xlfn.XLOOKUP(C10,Raw_Data_Transaksi!$A$1:$A$1001,Raw_Data_Transaksi!$C$1:$C$1001,,0) -> SLS-06 | C10: TRX-2025-0009 | D10: 45741 | E10: =VLOOKUP(B10,Master_Sales!$A$1:$D$9,2,FALSE) -> Fajar Nugraha | F10: =INDEX(Master_Sales!$D$1:$D$9,MATCH(Lembar_Kerja_Analisis!B10,Master_Sales!$A$1:$A$9,0)) -> Timur | G10: =INDEX(Master_Sales!$C$1:$C$9,MATCH(Lembar_Kerja_Analisis!B10,Master_Sales!$A$1:$A$9,0)) -> Makassar | H10: =VLOOKUP(A10,Master_Produk!$A$1:$E$16,2,FALSE) -> Celana Chino Slim Fit | I10: =INDEX(Master_Produk!$C$1:$C$16,MATCH(Lembar_Kerja_Analisis!A10,Master_Produk!$A$1:$A$16,0)) -> Fashion | J10: =_xlfn.XLOOKUP(A10,Master_Produk!$A$1:$A$16,Master_Produk!$D$1:$D$16,,0) -> 280000 | K10: =INDEX(Master_Produk!$E$1:$E$16,MATCH(Lembar_Kerja_Analisis!A10,Master_Produk!$A$1:$A$16,0)) -> 175000 | L10: 4 | M10: =L10*J10 -> 1120000 | N10: 0.1 | O10: =M10*N10 -> 112000 | P10: =M10-O10 -> 1008000 | Q10: =L10*K10 -> 700000 | R10: =P10-Q10 -> 308000
A11: =_xlfn.XLOOKUP(C11,Raw_Data_Transaksi!$A$1:$A$1001,Raw_Data_Transaksi!$D$1:$D$1001,,0) -> PRD-112 | B11: =_xlfn.XLOOKUP(C11,Raw_Data_Transaksi!$A$1:$A$1001,Raw_Data_Transaksi!$C$1:$C$1001,,0) -> SLS-04 | C11: TRX-2025-0010 | D11: 45931 | E11: =VLOOKUP(B11,Master_Sales!$A$1:$D$9,2,FALSE) -> Dewi Anggraini | F11: =INDEX(Master_Sales!$D$1:$D$9,MATCH(Lembar_Kerja_Analisis!B11,Master_Sales!$A$1:$A$9,0)) -> Barat | G11: =INDEX(Master_Sales!$C$1:$C$9,MATCH(Lembar_Kerja_Analisis!B11,Master_Sales!$A$1:$A$9,0)) -> Medan | H11: =VLOOKUP(A11,Master_Produk!$A$1:$E$16,2,FALSE) -> Susu UHT Full Cream 1L | I11: =INDEX(Master_Produk!$C$1:$C$16,MATCH(Lembar_Kerja_Analisis!A11,Master_Produk!$A$1:$A$16,0)) -> F&B | J11: =_xlfn.XLOOKUP(A11,Master_Produk!$A$1:$A$16,Master_Produk!$D$1:$D$16,,0) -> 22000 | K11: =INDEX(Master_Produk!$E$1:$E$16,MATCH(Lembar_Kerja_Analisis!A11,Master_Produk!$A$1:$A$16,0)) -> 18000 | L11: 17 | M11: =L11*J11 -> 374000 | N11: 0.15 | O11: =M11*N11 -> 56100 | P11: =M11-O11 -> 317900 | Q11: =L11*K11 -> 306000 | R11: =P11-Q11 -> 11900
A12: =_xlfn.XLOOKUP(C12,Raw_Data_Transaksi!$A$1:$A$1001,Raw_Data_Transaksi!$D$1:$D$1001,,0) -> PRD-106 | B12: =_xlfn.XLOOKUP(C12,Raw_Data_Transaksi!$A$1:$A$1001,Raw_Data_Transaksi!$C$1:$C$1001,,0) -> SLS-01 | C12: TRX-2025-0011 | D12: 46008 | E12: =VLOOKUP(B12,Master_Sales!$A$1:$D$9,2,FALSE) -> Andi Pratama | F12: =INDEX(Master_Sales!$D$1:$D$9,MATCH(Lembar_Kerja_Analisis!B12,Master_Sales!$A$1:$A$9,0)) -> Barat | G12: =INDEX(Master_Sales!$C$1:$C$9,MATCH(Lembar_Kerja_Analisis!B12,Master_Sales!$A$1:$A$9,0)) -> Jakarta | H12: =VLOOKUP(A12,Master_Produk!$A$1:$E$16,2,FALSE) -> Celana Chino Slim Fit | I12: =INDEX(Master_Produk!$C$1:$C$16,MATCH(Lembar_Kerja_Analisis!A12,Master_Produk!$A$1:$A$16,0)) -> Fashion | J12: =_xlfn.XLOOKUP(A12,Master_Produk!$A$1:$A$16,Master_Produk!$D$1:$D$16,,0) -> 280000 | K12: =INDEX(Master_Produk!$E$1:$E$16,MATCH(Lembar_Kerja_Analisis!A12,Master_Produk!$A$1:$A$16,0)) -> 175000 | L12: 4 | M12: =L12*J12 -> 1120000 | N12: 0 | O12: =M12*N12 -> 0 | P12: =M12-O12 -> 1120000 | Q12: =L12*K12 -> 700000 | R12: =P12-Q12 -> 420000
A13: =_xlfn.XLOOKUP(C13,Raw_Data_Transaksi!$A$1:$A$1001,Raw_Data_Transaksi!$D$1:$D$1001,,0) -> PRD-104 | B13: =_xlfn.XLOOKUP(C13,Raw_Data_Transaksi!$A$1:$A$1001,Raw_Data_Transaksi!$C$1:$C$1001,,0) -> SLS-06 | C13: TRX-2025-0012 | D13: 45691 | E13: =VLOOKUP(B13,Master_Sales!$A$1:$D$9,2,FALSE) -> Fajar Nugraha | F13: =INDEX(Master_Sales!$D$1:$D$9,MATCH(Lembar_Kerja_Analisis!B13,Master_Sales!$A$1:$A$9,0)) -> Timur | G13: =INDEX(Master_Sales!$C$1:$C$9,MATCH(Lembar_Kerja_Analisis!B13,Master_Sales!$A$1:$A$9,0)) -> Makassar | H13: =VLOOKUP(A13,Master_Produk!$A$1:$E$16,2,FALSE) -> Monitor 24" FHD 144Hz | I13: =INDEX(Master_Produk!$C$1:$C$16,MATCH(Lembar_Kerja_Analisis!A13,Master_Produk!$A$1:$A$16,0)) -> Elektronik | J13: =_xlfn.XLOOKUP(A13,Master_Produk!$A$1:$A$16,Master_Produk!$D$1:$D$16,,0) -> 1950000 | K13: =INDEX(Master_Produk!$E$1:$E$16,MATCH(Lembar_Kerja_Analisis!A13,Master_Produk!$A$1:$A$16,0)) -> 1500000 | L13: 4 | M13: =L13*J13 -> 7800000 | N13: 0.15 | O13: =M13*N13 -> 1170000 | P13: =M13-O13 -> 6630000 | Q13: =L13*K13 -> 6000000 | R13: =P13-Q13 -> 630000
... A1001: =_xlfn.XLOOKUP(C1001,Raw_Data_Transaksi!$A$1:$A$1001,Raw_Data_Transaksi!$D$1:$D$1001,,0) -> PRD-110 | B1001: =_xlfn.XLOOKUP(C1001,Raw_Data_Transaksi!$A$1:$A$1001,Raw_Data_Transaksi!$C$1:$C$1001,,0) -> SLS-07 | C1001: TRX-2025-1000 | D1001: 45916 | E1001: =VLOOKUP(B1001,Master_Sales!$A$1:$D$9,2,FALSE) -> Gita Permata | F1001: =INDEX(Master_Sales!$D$1:$D$9,MATCH(Lembar_Kerja_Analisis!B1001,Master_Sales!$A$1:$A$9,0)) -> Tengah | G1001: =INDEX(Master_Sales!$C$1:$C$9,MATCH(Lembar_Kerja_Analisis!B1001,Master_Sales!$A$1:$A$9,0)) -> Denpasar | H1001: =VLOOKUP(A1001,Master_Produk!$A$1:$E$16,2,FALSE) -> Minyak Goreng Sawit 2L | I1001: =INDEX(Master_Produk!$C$1:$C$16,MATCH(Lembar_Kerja_Analisis!A1001,Master_Produk!$A$1:$A$16,0)) -> F&B | J1001: =_xlfn.XLOOKUP(A1001,Master_Produk!$A$1:$A$16,Master_Produk!$D$1:$D$16,,0) -> 36000 | K1001: =INDEX(Master_Produk!$E$1:$E$16,MATCH(Lembar_Kerja_Analisis!A1001,Master_Produk!$A$1:$A$16,0)) -> 31000 | L1001: 15 | M1001: =L1001*J1001 -> 540000 | N1001: 0.1 | O1001: =M1001*N1001 -> 54000 | P1001: =M1001-O1001 -> 486000 | Q1001: =L1001*K1001 -> 465000 | R1001: =P1001-Q1001 -> 21000

Sheet PT_Sales_Performance
A3: Region | B3: Sales_Name | C3: Sum of Net_Revenue | D3: Sum of Discount_Pct | E3: Sum of Total_Profit | F3: Sum of % Profit Margin
A4: Barat | B4: Andi Pratama | C4: 394643400 | D4: 12.55 | E4: 66443400 | F4: 0.16836313
B5: Citra Lestari | C5: 660508700 | D5: 13.5 | E5: 90165700 | F5: 0.13650948
B6: Dewi Anggraini | C6: 421427200 | D6: 11.85 | E6: 43809200 | F6: 0.10395437
A7: Barat Total | C7: 1476579300 | D7: 37.9 | E7: 200418300 | F7: 0.13573148
A8: Tengah | B8: Eko Prasetyo | C8: 624703450 | D8: 13.1 | E8: 82129450 | F8: 0.1314695
B9: Gita Permata | C9: 818202450 | D9: 13.35 | E9: 78706450 | F9: 0.096194347
B10: Hendra Wijaya | C10: 774059450 | D10: 12.5 | E10: 87810450 | F10: 0.11344148
A11: Tengah Total | C11: 2216965350 | D11: 38.95 | E11: 248646350 | F11: 0.11215617
A12: Timur | B12: Budi Santoso | C12: 881718300 | D12: 14.5 | E12: 96042300 | F12: 0.10892629
B13: Fajar Nugraha | C13: 804883050 | D13: 12.05 | E13: 89000050 | F13: 0.11057513
A14: Timur Total | C14: 1686601350 | D14: 26.55 | E14: 185042350 | F14: 0.10971315
A15: Grand Total | C15: 5380146000 | D15: 103.4 | E15: 634107000 | F15: 0.11786056
